renderable/__init__.py
renderable-0.0.1.dist-info/LICENSE
renderable-0.0.1.dist-info/METADATA
renderable-0.0.1.dist-info/WHEEL
renderable-0.0.1.dist-info/top_level.txt
renderable-0.0.1.dist-info/RECORD
