Metadata-Version: 2.1
Name: renderable
Version: 0.0.1
Summary: Render stuff
Author: Chris Cardillo
Author-email: cfcardillo23@gmail.com
Classifier: Programming Language :: Python :: 3
Classifier: License :: OSI Approved :: MIT License
Classifier: Operating System :: OS Independent
Requires-Python: >=3.6
License-File: LICENSE
